setup.py
isolcss/__init__.py
isolcss/main.py
isolcss/parser.py
isolcss/tests.py
isolcss.egg-info/PKG-INFO
isolcss.egg-info/SOURCES.txt
isolcss.egg-info/dependency_links.txt
isolcss.egg-info/requires.txt
isolcss.egg-info/top_level.txt