Metadata-Version: 1.0
Name: isolcss
Version: 1.1.2
Summary: CSS isolator
Home-page: https://github.com/pagepart/isolcss
Author: PagePart Team
Author-email: opensource@pagepart.com
License: BSD
Platform: UNKNOWN
